event_subscriber/__init__.py
event_subscriber/subscriber.py
event_subscriber-0.1.5.dist-info/METADATA
event_subscriber-0.1.5.dist-info/WHEEL
event_subscriber-0.1.5.dist-info/entry_points.txt
event_subscriber-0.1.5.dist-info/top_level.txt
event_subscriber-0.1.5.dist-info/RECORD
