Metadata-Version: 2.1
Name: event_subscriber
Version: 0.1.5
Summary: A tool to subscribe and handle Ethereum events
Author: 5m477
Author-email: 5m477code@gmail.com
Classifier: Programming Language :: Python :: 3
Classifier: License :: OSI Approved :: MIT License
Classifier: Operating System :: OS Independent
Requires-Python: >=3.6
Requires-Dist: web3
Requires-Dist: colorama
Requires-Dist: pyfiglet
Requires-Dist: argparse
